{"name":"Tobin","weaponChain":[],"specialChain":[],"aChain":[],"bChain":[],"hpGrowth":0,"atkGrowth":0,"spdGrowth":0,"defGrowth":0,"resGrowth":0,"movementType":"INFANTRY","weaponType":"SWORD"}
{"name":"Abel","weaponChain":[71,131,22,23],"specialChain":[20025,20001],"aChain":[30033,30034,30035],"bChain":[40064,40065,40066],"hpGrowth":6,"atkGrowth":8,"spdGrowth":7,"defGrowth":4,"resGrowth":5,"movementType":"CAVALRY","weaponType":"LANCE"}
{"name":"Alfonse","weaponChain":[72,132,122,54],"specialChain":[20011,20044],"aChain":[30011,30012,30013],"cChain":[50029,50030,50031],"hpGrowth":7,"atkGrowth":8,"spdGrowth":5,"defGrowth":7,"resGrowth":4,"movementType":"INFANTRY","weaponType":"SWORD"}
{"name":"Alm","weaponChain":[72,132,122,39],"specialChain":[20014,20012],"aChain":[30004,30005,30006],"bChain":[40078,40079,40080],"hpGrowth":7,"atkGrowth":7,"spdGrowth":7,"defGrowth":6,"resGrowth":4,"movementType":"INFANTRY","weaponType":"SWORD"}
{"name":"Anna","weaponChain":[68,128,114,91],"specialChain":[20034,20003],"bChain":[40067,40068,40069],"cChain":[50035,50036,50037],"hpGrowth":6,"atkGrowth":6,"spdGrowth":9,"defGrowth":4,"resGrowth":6,"movementType":"INFANTRY","weaponType":"AXE"}
{"name":"Arthur","weaponChain":[68,128,36,37],"assistChain":[10021],"aChain":[30033,30034,30035],"bChain":[40027,40028,40029],"hpGrowth":7,"atkGrowth":7,"spdGrowth":6,"defGrowth":6,"resGrowth":5,"movementType":"INFANTRY","weaponType":"AXE"}
{"name":"Athena","weaponChain":[72,132,137,138],"specialChain":[20033,20032],"aChain":[30001,30075,30076],"cChain":[50073,50074,50075],"hpGrowth":5,"atkGrowth":7,"spdGrowth":9,"defGrowth":5,"resGrowth":5,"movementType":"INFANTRY","weaponType":"SWORD"}
{"name":"Azama","weaponChain":[7,92],"specialChain":[20028,20045],"assistChain":[10004,10014,10005],"cChain":[50041,50042,50043],"hpGrowth":7,"atkGrowth":4,"spdGrowth":5,"defGrowth":7,"resGrowth":5,"movementType":"INFANTRY","weaponType":"STAFF"}
{"name":"Azura","weaponChain":[71,131,110,111],"assistChain":[10019],"aChain":[30042,30043,30044],"cChain":[50011,50012,50013],"hpGrowth":5,"atkGrowth":8,"spdGrowth":8,"defGrowth":4,"resGrowth":6,"movementType":"INFANTRY","weaponType":"LANCE"}
{"name":"Barst","weaponChain":[68,128,18,19],"assistChain":[10017],"bChain":[40026],"cChain":[50029,50030,50031],"hpGrowth":8,"atkGrowth":7,"spdGrowth":7,"defGrowth":7,"resGrowth":2,"movementType":"INFANTRY","weaponType":"AXE"}
{"name":"Bartre","weaponChain":[68,128,63,64],"assistChain":[10020],"aChain":[30030,30031,30032],"bChain":[40010,40011,40012],"hpGrowth":9,"atkGrowth":8,"spdGrowth":5,"defGrowth":8,"resGrowth":1,"movementType":"INFANTRY","weaponType":"AXE"}
{"name":"Beruka","weaponChain":[68,128,73,74],"specialChain":[20034,20018],"aChain":[30020,30021,30022],"bChain":[40033],"hpGrowth":8,"atkGrowth":6,"spdGrowth":4,"defGrowth":9,"resGrowth":4,"movementType":"FLIER","weaponType":"AXE"}
{"name":"Boey","weaponChain":[136,35,151,152],"specialChain":[20019,20027],"aChain":[30064,30065,30066],"bChain":[40049,40050,40051],"hpGrowth":7,"atkGrowth":6,"spdGrowth":6,"defGrowth":7,"resGrowth":2,"movementType":"INFANTRY","weaponType":"GTOME"}
{"name":"Caeda","weaponChain":[72,132,3,4],"assistChain":[10012],"aChain":[30008,30009,30010],"cChain":[50011,50012,50010],"hpGrowth":5,"atkGrowth":5,"spdGrowth":9,"defGrowth":5,"resGrowth":7,"movementType":"FLIER","weaponType":"SWORD"}
{"name":"CaedaBridal","weaponChain":[134,34,161,156],"specialChain":[20010,20026],"aChain":[30039,30067,30068],"cChain":[50023,50024,50025],"hpGrowth":4,"atkGrowth":6,"spdGrowth":9,"defGrowth":3,"resGrowth":6,"movementType":"INFANTRY","weaponType":"BTOME"}
{"name":"Cain","weaponChain":[72,132,24,25],"specialChain":[20009,20015],"bChain":[40073,40074,40075],"cChain":[50041,50042,50043],"hpGrowth":7,"atkGrowth":7,"spdGrowth":8,"defGrowth":5,"resGrowth":3,"movementType":"CAVALRY","weaponType":"SWORD"}
{"name":"Camilla","weaponChain":[68,128,18,19],"specialChain":[20014,20012],"aChain":[30008,30009,30010],"cChain":[50026,50027,50028],"hpGrowth":5,"atkGrowth":6,"spdGrowth":7,"defGrowth":6,"resGrowth":7,"movementType":"FLIER","weaponType":"AXE"}
{"name":"CamillaEaster","weaponChain":[136,35,166,142],"assistChain":[10009],"aChain":[30026,30027,30028],"bChain":[40077],"hpGrowth":6,"atkGrowth":8,"spdGrowth":5,"defGrowth":6,"resGrowth":3,"movementType":"FLIER","weaponType":"GTOME"}
{"name":"Camus","weaponChain":[71,131,120,160],"specialChain":[20041,20022],"aChain":[30072],"cChain":[50029,50030,50015],"hpGrowth":7,"atkGrowth":7,"spdGrowth":7,"defGrowth":7,"resGrowth":2,"movementType":"CAVALRY","weaponType":"LANCE"}
{"name":"Catria","weaponChain":[71,131,77,78],"specialChain":[20033,20030],"aChain":[30001,30002,30003],"bChain":[40052,40053,40054],"hpGrowth":6,"atkGrowth":7,"spdGrowth":7,"defGrowth":6,"resGrowth":5,"movementType":"FLIER","weaponType":"LANCE"}
{"name":"Cecilia","weaponChain":[136,35,59,60],"assistChain":[10011],"aChain":[30004,30005,30006],"bChain":[40020,40021,40022],"hpGrowth":5,"atkGrowth":7,"spdGrowth":5,"defGrowth":4,"resGrowth":6,"movementType":"CAVALRY","weaponType":"GTOME"}
{"name":"Celica","weaponChain":[44,33,16,150],"specialChain":[20040,20005],"aChain":[30061,30062,30063],"cChain":[50032,50033,50034],"hpGrowth":6,"atkGrowth":7,"spdGrowth":8,"defGrowth":4,"resGrowth":3,"movementType":"INFANTRY","weaponType":"RTOME"}
{"name":"CharlotteBridal","weaponChain":[71,131,162,157],"assistChain":[10020],"aChain":[30069,30070,30071],"cChain":[50041,50042,50043],"hpGrowth":8,"atkGrowth":8,"spdGrowth":7,"defGrowth":5,"resGrowth":3,"movementType":"INFANTRY","weaponType":"LANCE"}
{"name":"Cherche","weaponChain":[68,128,63,64],"assistChain":[10008],"aChain":[30004,30005,30006],"cChain":[50006,50007,50008],"hpGrowth":8,"atkGrowth":9,"spdGrowth":5,"defGrowth":7,"resGrowth":2,"movementType":"FLIER","weaponType":"AXE"}
{"name":"Chrom","weaponChain":[72,132,122,39],"specialChain":[20011,20044,20002],"aChain":[30020,30021,30022],"cChain":[50032,50033,50034],"hpGrowth":8,"atkGrowth":9,"spdGrowth":5,"defGrowth":7,"resGrowth":2,"movementType":"INFANTRY","weaponType":"SWORD"}
{"name":"ChromEaster","weaponChain":[68,128,164,140],"assistChain":[10018],"aChain":[30014,30073,30053],"cChain":[50066,50067,50056],"hpGrowth":7,"atkGrowth":8,"spdGrowth":7,"defGrowth":6,"resGrowth":3,"movementType":"INFANTRY","weaponType":"AXE"}
{"name":"Clair","weaponChain":[71,131,120,121],"assistChain":[10003],"bChain":[40081],"cChain":[50038,50039,50040],"hpGrowth":5,"atkGrowth":5,"spdGrowth":9,"defGrowth":5,"resGrowth":7,"movementType":"FLIER","weaponType":"LANCE"}
{"name":"Clarine","weaponChain":[7,40],"specialChain":[20028,20047],"assistChain":[10004,10014,10005],"aChain":[30039,30040,30041],"hpGrowth":5,"atkGrowth":5,"spdGrowth":7,"defGrowth":4,"resGrowth":6,"movementType":"CAVALRY","weaponType":"STAFF"}
{"name":"Clarisse","weaponChain":[69,129,192,193],"specialChain":[20034,20018],"bChain":[40040,40041,40042],"cChain":[50044,50045,50046],"hpGrowth":5,"atkGrowth":7,"spdGrowth":8,"defGrowth":5,"resGrowth":3,"movementType":"INFANTRY","weaponType":"BOW"}
{"name":"Cordelia","weaponChain":[71,131,22,23],"specialChain":[20034,20003,20016],"aChain":[30046,30047,30048],"bChain":[40037,40038,40039],"hpGrowth":6,"atkGrowth":8,"spdGrowth":8,"defGrowth":4,"resGrowth":5,"movementType":"FLIER","weaponType":"LANCE"}
{"name":"CordeliaBridal","weaponChain":[69,129,163,158],"assistChain":[10009,10022],"bChain":[40020,40021,40022],"cChain":[50001,50002,50003],"hpGrowth":5,"atkGrowth":8,"spdGrowth":8,"defGrowth":3,"resGrowth":4,"movementType":"INFANTRY","weaponType":"BOW"}
{"name":"CorrinF","weaponChain":[168,169,28,29],"specialChain":[20014,20012],"bChain":[40058,40059,40060],"cChain":[50018,50019,50020],"hpGrowth":6,"atkGrowth":5,"spdGrowth":9,"defGrowth":8,"resGrowth":3,"movementType":"INFANTRY","weaponType":"BBREATH"}
{"name":"CorrinM","weaponChain":[72,132,122,139],"specialChain":[20014,20013],"aChain":[30014,30015,30016],"bChain":[40034,40035,40036],"hpGrowth":6,"atkGrowth":7,"spdGrowth":7,"defGrowth":6,"resGrowth":5,"movementType":"INFANTRY","weaponType":"SWORD"}
{"name":"Donnel","weaponChain":[71,131,22,23],"assistChain":[10013],"aChain":[30033,30034,30035],"bChain":[40019],"hpGrowth":8,"atkGrowth":9,"spdGrowth":7,"defGrowth":8,"resGrowth":5,"movementType":"INFANTRY","weaponType":"LANCE"}
{"name":"Draug","weaponChain":[72,132,24,25],"specialChain":[20009,20036],"bChain":[40033],"cChain":[50032,50033,50053],"hpGrowth":8,"atkGrowth":6,"spdGrowth":8,"defGrowth":8,"resGrowth":3,"movementType":"ARMOR","weaponType":"SWORD"}
{"name":"Effie","weaponChain":[71,131,120,121],"assistChain":[10020],"aChain":[30011,30012,30013],"bChain":[40070,40071,40072],"hpGrowth":9,"atkGrowth":9,"spdGrowth":4,"defGrowth":6,"resGrowth":5,"movementType":"ARMOR","weaponType":"LANCE"}
{"name":"Eirika","weaponChain":[72,132,122,112],"assistChain":[10008],"bChain":[40019],"cChain":[50023,50024,50025],"hpGrowth":7,"atkGrowth":5,"spdGrowth":8,"defGrowth":5,"resGrowth":6,"movementType":"INFANTRY","weaponType":"SWORD"}
{"name":"Eldigan","weaponChain":[72,132,79,89],"specialChain":[20040,20021],"aChain":[30030,30031,30032],"bChain":[40033],"hpGrowth":8,"atkGrowth":7,"spdGrowth":5,"defGrowth":8,"resGrowth":2,"movementType":"CAVALRY","weaponType":"SWORD"}
{"name":"Elise","weaponChain":[7,56],"specialChain":[20028,20029],"assistChain":[10004,10006,10015],"bChain":[40030,40031,40032],"hpGrowth":3,"atkGrowth":7,"spdGrowth":7,"defGrowth":3,"resGrowth":7,"movementType":"CAVALRY","weaponType":"STAFF"}
{"name":"Eliwood","weaponChain":[72,132,122,32],"specialChain":[20025,20043],"bChain":[40001,40002,40003],"cChain":[50035,50036,50054],"hpGrowth":6,"atkGrowth":7,"spdGrowth":6,"defGrowth":4,"resGrowth":7,"movementType":"CAVALRY","weaponType":"SWORD"}
{"name":"Ephraim","weaponChain":[71,131,66,113],"specialChain":[20033,20032],"bChain":[40055,40056,40057],"cChain":[50044,50045,50046],"hpGrowth":8,"atkGrowth":8,"spdGrowth":5,"defGrowth":7,"resGrowth":3,"movementType":"INFANTRY","weaponType":"LANCE"}
{"name":"Est","weaponChain":[71,131,66,67],"assistChain":[10018],"aChain":[30023,30024,30025],"bChain":[40061,40062,40063],"hpGrowth":5,"atkGrowth":8,"spdGrowth":6,"defGrowth":5,"resGrowth":7,"movementType":"FLIER","weaponType":"LANCE"}
{"name":"Fae","weaponChain":[170,171,82,83],"assistChain":[10002],"bChain":[40049,40050,40051],"cChain":[50041,50042,50043],"hpGrowth":10,"atkGrowth":9,"spdGrowth":7,"defGrowth":5,"resGrowth":6,"movementType":"INFANTRY","weaponType":"GBREATH"}
{"name":"Faye","weaponChain":[69,129,144,145],"specialChain":[20011,20035],"bChain":[40073,40074,40075],"cChain":[50057,50058,50059],"hpGrowth":8,"atkGrowth":7,"spdGrowth":6,"defGrowth":6,"resGrowth":7,"movementType":"INFANTRY","weaponType":"BOW"}
{"name":"Felicia","weaponChain":[70,130,118,119],"specialChain":[20010,20017],"aChain":[30039,30040,30041],"cChain":[50001,50002,50003],"hpGrowth":5,"atkGrowth":4,"spdGrowth":8,"defGrowth":3,"resGrowth":8,"movementType":"INFANTRY","weaponType":"DAGGER"}
{"name":"Fir","weaponChain":[72,132,79,80],"specialChain":[20010,20017],"aChain":[30042,30043,30044],"bChain":[40037,40038,40039],"hpGrowth":6,"atkGrowth":5,"spdGrowth":8,"defGrowth":5,"resGrowth":7,"movementType":"INFANTRY","weaponType":"SWORD"}
{"name":"Florina","weaponChain":[71,131,66,67],"assistChain":[10000],"aChain":[30008,30009,30010],"cChain":[50001,50002,50003],"hpGrowth":7,"atkGrowth":6,"spdGrowth":5,"defGrowth":5,"resGrowth":8,"movementType":"FLIER","weaponType":"LANCE"}
{"name":"Frederick","weaponChain":[68,128,63,64],"specialChain":[20033,20030],"bChain":[40073,40074,40075],"cChain":[50006,50007,50008],"hpGrowth":7,"atkGrowth":8,"spdGrowth":5,"defGrowth":9,"resGrowth":1,"movementType":"CAVALRY","weaponType":"AXE"}
{"name":"FrederickSummer","weaponChain":[70,130,194,195],"assistChain":[10000],"aChain":[30001,30002,30003],"bChain":[40061,40094,40095],"hpGrowth":6,"atkGrowth":7,"spdGrowth":7,"defGrowth":6,"resGrowth":2,"movementType":"INFANTRY","weaponType":"DAGGER"}
{"name":"Gaius","weaponChain":[70,130,105,106],"assistChain":[10012],"aChain":[30017,30018,30019],"bChain":[40037,40038,40039],"hpGrowth":7,"atkGrowth":6,"spdGrowth":8,"defGrowth":4,"resGrowth":3,"movementType":"INFANTRY","weaponType":"DAGGER"}
{"name":"GaiusSummer","weaponChain":[69,129,196,197],"specialChain":[20034,20003],"bChain":[40067,40068,40069],"cChain":[50079,50080,50081],"hpGrowth":4,"atkGrowth":6,"spdGrowth":9,"defGrowth":3,"resGrowth":6,"movementType":"INFANTRY","weaponType":"BOW"}
{"name":"Genny","weaponChain":[7,56],"specialChain":[20028,20024],"assistChain":[10004,10006,10007],"bChain":[40088,40089,40090],"hpGrowth":3,"atkGrowth":8,"spdGrowth":5,"defGrowth":4,"resGrowth":8,"movementType":"INFANTRY","weaponType":"STAFF"}
{"name":"Gordin","weaponChain":[69,129,20,21],"assistChain":[10018],"aChain":[30004,30005,30006],"bChain":[40067,40068,40069],"hpGrowth":7,"atkGrowth":7,"spdGrowth":5,"defGrowth":7,"resGrowth":2,"movementType":"INFANTRY","weaponType":"BOW"}
{"name":"Gunter","weaponChain":[68,128,114,115],"assistChain":[10003],"aChain":[30001,30002,30003],"cChain":[50018,50019,50021],"hpGrowth":6,"atkGrowth":6,"spdGrowth":4,"defGrowth":6,"resGrowth":2,"movementType":"CAVALRY","weaponType":"AXE"}
{"name":"Gwendolyn","weaponChain":[71,131,77,78],"specialChain":[20009,20015],"bChain":[40019],"cChain":[50018,50019,50017],"hpGrowth":8,"atkGrowth":6,"spdGrowth":5,"defGrowth":8,"resGrowth":6,"movementType":"ARMOR","weaponType":"LANCE"}
{"name":"Hana","weaponChain":[72,132,3,4],"assistChain":[10009],"aChain":[30036,30037,30038],"bChain":[40034,40035,40036],"hpGrowth":5,"atkGrowth":8,"spdGrowth":8,"defGrowth":4,"resGrowth":6,"movementType":"INFANTRY","weaponType":"SWORD"}
{"name":"Hawkeye","weaponChain":[68,128,73,74],"specialChain":[20040,20021],"aChain":[30011,30012,30013],"cChain":[50041,50042,50043],"hpGrowth":7,"atkGrowth":7,"spdGrowth":4,"defGrowth":6,"resGrowth":7,"movementType":"INFANTRY","weaponType":"AXE"}
{"name":"Hector","weaponChain":[68,128,114,2],"specialChain":[20009,20036],"aChain":[30029],"cChain":[50029,50030,50014],"hpGrowth":9,"atkGrowth":8,"spdGrowth":5,"defGrowth":8,"resGrowth":3,"movementType":"ARMOR","weaponType":"AXE"}
{"name":"Henry","weaponChain":[53,109,100,101],"specialChain":[20019,20027],"aChain":[30020,30021,30022],"bChain":[40023,40024,40025],"hpGrowth":8,"atkGrowth":4,"spdGrowth":4,"defGrowth":7,"resGrowth":5,"movementType":"INFANTRY","weaponType":"RTOME"}
{"name":"Hinata","weaponChain":[72,132,107,108],"specialChain":[20009,20036],"aChain":[30030,30031,30032],"bChain":[40010,40011,40012],"hpGrowth":8,"atkGrowth":7,"spdGrowth":5,"defGrowth":8,"resGrowth":3,"movementType":"INFANTRY","weaponType":"SWORD"}
{"name":"Hinoka","weaponChain":[71,131,22,23],"specialChain":[20042,20007],"aChain":[30020,30021,30022],"cChain":[50023,50024,50022],"hpGrowth":6,"atkGrowth":9,"spdGrowth":7,"defGrowth":5,"resGrowth":4,"movementType":"FLIER","weaponType":"LANCE"}
{"name":"Ike","weaponChain":[72,132,122,147],"specialChain":[20033,20030,20002],"aChain":[30058,30059,30060],"bChain":[40064,40065,40066],"hpGrowth":7,"atkGrowth":8,"spdGrowth":7,"defGrowth":7,"resGrowth":2,"movementType":"INFANTRY","weaponType":"SWORD"}
{"name":"Jaffar","weaponChain":[70,130,118,30],"specialChain":[20034,20018],"aChain":[30036,30037,30038],"cChain":[50050,50051,50052],"hpGrowth":7,"atkGrowth":5,"spdGrowth":7,"defGrowth":5,"resGrowth":4,"movementType":"INFANTRY","weaponType":"DAGGER"}
{"name":"Jagen","weaponChain":[71,131,120,121],"specialChain":[20025,20001],"aChain":[30030,30031,30032],"cChain":[50011,50012,50005],"hpGrowth":4,"atkGrowth":5,"spdGrowth":4,"defGrowth":4,"resGrowth":7,"movementType":"CAVALRY","weaponType":"LANCE"}
{"name":"Jakob","weaponChain":[70,130,118,119],"assistChain":[10011],"aChain":[30014,30015,30016],"bChain":[40049,40050,40051],"hpGrowth":6,"atkGrowth":6,"spdGrowth":6,"defGrowth":5,"resGrowth":5,"movementType":"INFANTRY","weaponType":"DAGGER"}
{"name":"Jeorge","weaponChain":[69,129,116,94],"specialChain":[20039,20004],"bChain":[40052,40053,40054],"cChain":[50038,50039,50040],"hpGrowth":5,"atkGrowth":7,"spdGrowth":7,"defGrowth":5,"resGrowth":4,"movementType":"INFANTRY","weaponType":"BOW"}
{"name":"Julia","weaponChain":[136,35,104,90],"specialChain":[20014,20013],"aChain":[30039,30040,30041],"cChain":[50001,50002,50003],"hpGrowth":6,"atkGrowth":8,"spdGrowth":5,"defGrowth":2,"resGrowth":7,"movementType":"INFANTRY","weaponType":"GTOME"}
{"name":"Kagero","weaponChain":[70,130,95,96],"specialChain":[20038,20037],"aChain":[30049,30050,30051],"bChain":[40013,40014,40015],"hpGrowth":3,"atkGrowth":8,"spdGrowth":7,"defGrowth":4,"resGrowth":6,"movementType":"INFANTRY","weaponType":"DAGGER"}
{"name":"Karel","weaponChain":[72,132,137,138],"specialChain":[20038,20037],"aChain":[30017,30018,30019],"bChain":[40016,40017,40018],"hpGrowth":9,"atkGrowth":6,"spdGrowth":8,"defGrowth":5,"resGrowth":3,"movementType":"INFANTRY","weaponType":"SWORD"}
{"name":"Katarina","weaponChain":[44,33,188,186],"specialChain":[20010,20017],"aChain":[30011,30074,30054],"cChain":[50068,50069,50070],"hpGrowth":4,"atkGrowth":8,"spdGrowth":8,"defGrowth":1,"resGrowth":7,"movementType":"INFANTRY","weaponType":"RTOME"}
{"name":"Klein","weaponChain":[69,129,20,21],"specialChain":[20010,20017],"aChain":[30011,30012,30013],"bChain":[40043,40044,40045],"hpGrowth":6,"atkGrowth":6,"spdGrowth":8,"defGrowth":3,"resGrowth":5,"movementType":"INFANTRY","weaponType":"BOW"}
{"name":"Lachesis","weaponChain":[7,1],"specialChain":[20028,20045],"assistChain":[10004,10006,10007],"cChain":[50035,50036,50037],"hpGrowth":6,"atkGrowth":8,"spdGrowth":4,"defGrowth":4,"resGrowth":6,"movementType":"INFANTRY","weaponType":"STAFF"}
{"name":"Laslow","weaponChain":[72,132,122,123],"specialChain":[20011,20035],"bChain":[40001,40002,40003],"cChain":[50023,50024,50025],"hpGrowth":7,"atkGrowth":8,"spdGrowth":5,"defGrowth":7,"resGrowth":4,"movementType":"INFANTRY","weaponType":"SWORD"}
{"name":"Legion","weaponChain":[68,128,190,191],"specialChain":[20038,20037],"aChain":[30030,30031,30032],"bChain":[40034,40035,40036],"hpGrowth":8,"atkGrowth":8,"spdGrowth":8,"defGrowth":4,"resGrowth":3,"movementType":"INFANTRY","weaponType":"AXE"}
{"name":"Leo","weaponChain":[53,109,41,26],"specialChain":[20040,20005],"bChain":[40043,40044,40045],"cChain":[50026,50027,50028],"hpGrowth":6,"atkGrowth":6,"spdGrowth":4,"defGrowth":5,"resGrowth":6,"movementType":"CAVALRY","weaponType":"RTOME"}
{"name":"Lilina","weaponChain":[44,33,16,17],"specialChain":[20039,20020],"aChain":[30004,30005,30006],"cChain":[50029,50030,50031],"hpGrowth":5,"atkGrowth":9,"spdGrowth":5,"defGrowth":3,"resGrowth":6,"movementType":"INFANTRY","weaponType":"RTOME"}
{"name":"Linde","weaponChain":[134,34,133,8],"assistChain":[10000],"aChain":[30042,30043,30044],"cChain":[50011,50012,50013],"hpGrowth":5,"atkGrowth":8,"spdGrowth":8,"defGrowth":1,"resGrowth":6,"movementType":"INFANTRY","weaponType":"BTOME"}
{"name":"Lissa","weaponChain":[7,56],"specialChain":[20028,20029],"assistChain":[10004,10014,10016],"bChain":[40049,40050,40051],"hpGrowth":6,"atkGrowth":5,"spdGrowth":5,"defGrowth":6,"resGrowth":6,"movementType":"INFANTRY","weaponType":"STAFF"}
{"name":"Lloyd","weaponChain":[72,132,122,155],"specialChain":[20010,20026],"bChain":[40037,40038,40039],"cChain":[50041,50042,50043],"hpGrowth":7,"atkGrowth":7,"spdGrowth":8,"defGrowth":3,"resGrowth":6,"movementType":"INFANTRY","weaponType":"SWORD"}
{"name":"Lonqu","weaponChain":[72,132,79,80],"specialChain":[20034,20018],"aChain":[30042,30043,30044],"bChain":[40067,40068,40069],"hpGrowth":8,"atkGrowth":6,"spdGrowth":9,"defGrowth":4,"resGrowth":4,"movementType":"INFANTRY","weaponType":"SWORD"}
{"name":"Lucina","weaponChain":[72,132,122,39],"specialChain":[20033,20030,20002],"aChain":[30026,30027,30028],"cChain":[50029,50030,50031],"hpGrowth":7,"atkGrowth":8,"spdGrowth":8,"defGrowth":5,"resGrowth":3,"movementType":"INFANTRY","weaponType":"SWORD"}
{"name":"LucinaEaster","weaponChain":[134,34,167,143],"assistChain":[10012],"aChain":[30008,30074,30054],"bChain":[40058,40059,40060],"hpGrowth":5,"atkGrowth":6,"spdGrowth":8,"defGrowth":4,"resGrowth":5,"movementType":"INFANTRY","weaponType":"BTOME"}
{"name":"Lucius","weaponChain":[7,92],"specialChain":[20028,20031],"assistChain":[10004,10014,10005],"aChain":[30033,30034,30035],"hpGrowth":5,"atkGrowth":8,"spdGrowth":6,"defGrowth":1,"resGrowth":8,"movementType":"INFANTRY","weaponType":"STAFF"}
{"name":"Lukas","weaponChain":[71,131,77,78],"specialChain":[20025,20043],"aChain":[30055,30056,30057],"bChain":[40034,40035,40036],"hpGrowth":8,"atkGrowth":8,"spdGrowth":4,"defGrowth":9,"resGrowth":2,"movementType":"INFANTRY","weaponType":"LANCE"}
{"name":"Luke","weaponChain":[72,132,24,25],"specialChain":[20019,20008],"aChain":[30077,30078,30079],"cChain":[50076,50077,50078],"hpGrowth":7,"atkGrowth":8,"spdGrowth":6,"defGrowth":6,"resGrowth":3,"movementType":"CAVALRY","weaponType":"SWORD"}
{"name":"Lyn","weaponChain":[72,132,122,127],"specialChain":[20034,20003,20016],"aChain":[30017,30018,30019],"cChain":[50038,50039,50040],"hpGrowth":5,"atkGrowth":6,"spdGrowth":8,"defGrowth":5,"resGrowth":7,"movementType":"INFANTRY","weaponType":"SWORD"}
{"name":"LynBridal","weaponChain":[7,159],"specialChain":[20028,20047],"assistChain":[10004,10014,10016],"bChain":[40091,40092,40093],"hpGrowth":6,"atkGrowth":6,"spdGrowth":7,"defGrowth":4,"resGrowth":5,"movementType":"INFANTRY","weaponType":"STAFF"}
{"name":"Mae","weaponChain":[134,34,153,154],"assistChain":[10002],"bChain":[40016,40017,40018],"cChain":[50063,50064,50065],"hpGrowth":5,"atkGrowth":8,"spdGrowth":7,"defGrowth":2,"resGrowth":6,"movementType":"INFANTRY","weaponType":"BTOME"}
{"name":"Maria","weaponChain":[7,93],"specialChain":[20028,20031],"assistChain":[10004,10006,10007],"cChain":[50011,50012,50013],"hpGrowth":5,"atkGrowth":6,"spdGrowth":8,"defGrowth":3,"resGrowth":6,"movementType":"INFANTRY","weaponType":"STAFF"}
{"name":"Marth","weaponChain":[72,132,122,39],"assistChain":[10008],"bChain":[40020,40021,40022],"cChain":[50038,50039,50040],"hpGrowth":6,"atkGrowth":7,"spdGrowth":8,"defGrowth":6,"resGrowth":4,"movementType":"INFANTRY","weaponType":"SWORD"}
{"name":"MaskedMarth","weaponChain":[72,132,122,39],"hpGrowth":7,"atkGrowth":8,"spdGrowth":8,"defGrowth":5,"resGrowth":3,"movementType":"INFANTRY","weaponType":"SWORD"}
{"name":"Matthew","weaponChain":[70,130,105,106],"assistChain":[10013],"bChain":[40040,40041,40042],"cChain":[50023,50024,50025],"hpGrowth":7,"atkGrowth":5,"spdGrowth":7,"defGrowth":7,"resGrowth":2,"movementType":"INFANTRY","weaponType":"DAGGER"}
{"name":"Merric","weaponChain":[136,35,104,38],"specialChain":[20042,20023],"aChain":[30033,30034,30035],"cChain":[50035,50036,50037],"hpGrowth":7,"atkGrowth":5,"spdGrowth":7,"defGrowth":6,"resGrowth":3,"movementType":"INFANTRY","weaponType":"GTOME"}
{"name":"Michalis","weaponChain":[68,128,114,65],"specialChain":[20041,20006],"aChain":[30052],"cChain":[50044,50045,50046],"hpGrowth":7,"atkGrowth":8,"spdGrowth":5,"defGrowth":8,"resGrowth":3,"movementType":"FLIER","weaponType":"AXE"}
{"name":"Minerva","weaponChain":[68,128,114,65],"specialChain":[20025,20043],"aChain":[30036,30037,30038],"cChain":[50032,50033,50055],"hpGrowth":6,"atkGrowth":7,"spdGrowth":7,"defGrowth":7,"resGrowth":4,"movementType":"FLIER","weaponType":"AXE"}
{"name":"Mist","weaponChain":[7,124],"specialChain":[20028,20031],"assistChain":[10004,10006,10015],"cChain":[50035,50060,50061],"hpGrowth":6,"atkGrowth":5,"spdGrowth":6,"defGrowth":3,"resGrowth":8,"movementType":"INFANTRY","weaponType":"STAFF"}
{"name":"Narcian","weaponChain":[68,128,36,37],"specialChain":[20038,20048],"bChain":[40027,40028,40029],"cChain":[50026,50027,50028],"hpGrowth":7,"atkGrowth":6,"spdGrowth":6,"defGrowth":7,"resGrowth":5,"movementType":"FLIER","weaponType":"AXE"}
{"name":"Navarre","weaponChain":[72,132,79,80],"specialChain":[20042,20007],"bChain":[40016,40017,40018],"cChain":[50050,50051,50052],"hpGrowth":7,"atkGrowth":7,"spdGrowth":8,"defGrowth":4,"resGrowth":5,"movementType":"INFANTRY","weaponType":"SWORD"}
{"name":"Niles","weaponChain":[69,129,75,76],"specialChain":[20010,20026],"aChain":[30049,30050,30051],"cChain":[50035,50036,50037],"hpGrowth":5,"atkGrowth":5,"spdGrowth":8,"defGrowth":2,"resGrowth":8,"movementType":"INFANTRY","weaponType":"BOW"}
{"name":"Ninian","weaponChain":[168,169,180,181],"assistChain":[10001],"bChain":[40020,40021,40022],"cChain":[50006,50007,50009],"hpGrowth":8,"atkGrowth":5,"spdGrowth":8,"defGrowth":4,"resGrowth":6,"movementType":"INFANTRY","weaponType":"BBREATH"}
{"name":"Nino","weaponChain":[136,35,57,58],"assistChain":[10002],"aChain":[30039,30040,30041],"cChain":[50018,50019,50020],"hpGrowth":4,"atkGrowth":8,"spdGrowth":8,"defGrowth":3,"resGrowth":5,"movementType":"INFANTRY","weaponType":"GTOME"}
{"name":"Nowi","weaponChain":[168,169,85,86],"assistChain":[10010],"aChain":[30014,30015,30016],"cChain":[50047,50048,50049],"hpGrowth":9,"atkGrowth":9,"spdGrowth":6,"defGrowth":7,"resGrowth":6,"movementType":"INFANTRY","weaponType":"BBREATH"}
{"name":"Oboro","weaponChain":[71,131,66,67],"assistChain":[10010],"bChain":[40055,40056,40057],"cChain":[50047,50048,50049],"hpGrowth":6,"atkGrowth":7,"spdGrowth":5,"defGrowth":8,"resGrowth":5,"movementType":"INFANTRY","weaponType":"LANCE"}
{"name":"Odin","weaponChain":[134,34,11,11],"specialChain":[20033,20032],"aChain":[30017,30018,30019],"bChain":[40046,40047,40048],"hpGrowth":7,"atkGrowth":4,"spdGrowth":7,"defGrowth":5,"resGrowth":5,"movementType":"INFANTRY","weaponType":"BTOME"}
{"name":"Ogma","weaponChain":[72,132,24,25],"specialChain":[20011,20035],"aChain":[30017,30018,30019],"cChain":[50029,50030,50031],"hpGrowth":8,"atkGrowth":9,"spdGrowth":7,"defGrowth":6,"resGrowth":1,"movementType":"INFANTRY","weaponType":"SWORD"}
{"name":"Olivia","weaponChain":[72,132,122,123],"assistChain":[10001],"bChain":[40026],"cChain":[50018,50019,50020],"hpGrowth":5,"atkGrowth":6,"spdGrowth":8,"defGrowth":6,"resGrowth":6,"movementType":"INFANTRY","weaponType":"SWORD"}
{"name":"Olwen","weaponChain":[134,34,133,31],"assistChain":[10017],"aChain":[30049,30050,30051],"cChain":[50035,50036,50054],"hpGrowth":4,"atkGrowth":5,"spdGrowth":8,"defGrowth":3,"resGrowth":7,"movementType":"CAVALRY","weaponType":"BTOME"}
{"name":"Palla","weaponChain":[72,132,107,108],"specialChain":[20033,20032],"bChain":[40073,40074,40075],"cChain":[50038,50039,50016],"hpGrowth":7,"atkGrowth":7,"spdGrowth":6,"defGrowth":6,"resGrowth":5,"movementType":"FLIER","weaponType":"SWORD"}
{"name":"Peri","weaponChain":[71,131,77,78],"specialChain":[20034,20018],"aChain":[30039,30040,30041],"cChain":[50044,50045,50046],"hpGrowth":5,"atkGrowth":7,"spdGrowth":7,"defGrowth":4,"resGrowth":7,"movementType":"CAVALRY","weaponType":"LANCE"}
{"name":"Priscilla","weaponChain":[7,93],"specialChain":[20028,20046],"assistChain":[10004,10014,10016],"cChain":[50032,50033,50034],"hpGrowth":5,"atkGrowth":6,"spdGrowth":6,"defGrowth":3,"resGrowth":7,"movementType":"CAVALRY","weaponType":"STAFF"}
{"name":"Raigh","weaponChain":[53,109,102,103],"assistChain":[10009],"aChain":[30033,30034,30035],"bChain":[40058,40059,40060],"hpGrowth":5,"atkGrowth":7,"spdGrowth":6,"defGrowth":4,"resGrowth":6,"movementType":"INFANTRY","weaponType":"RTOME"}
{"name":"Raven","weaponChain":[68,128,18,19],"specialChain":[20011,20044],"aChain":[30026,30027,30028],"cChain":[50044,50045,50046],"hpGrowth":6,"atkGrowth":8,"spdGrowth":8,"defGrowth":5,"resGrowth":4,"movementType":"INFANTRY","weaponType":"AXE"}
{"name":"Rebecca","weaponChain":[69,129,116,117],"assistChain":[10000],"aChain":[30008,30009,30010],"bChain":[40052,40053,40054],"hpGrowth":5,"atkGrowth":6,"spdGrowth":8,"defGrowth":3,"resGrowth":6,"movementType":"INFANTRY","weaponType":"BOW"}
{"name":"Reinhardt","weaponChain":[134,34,133,31],"specialChain":[20041,20006],"bChain":[40067,40068,40069],"cChain":[50029,50030,50015],"hpGrowth":6,"atkGrowth":7,"spdGrowth":4,"defGrowth":6,"resGrowth":4,"movementType":"CAVALRY","weaponType":"BTOME"}
{"name":"RobinF","weaponChain":[136,35,61,62],"specialChain":[20019,20027],"aChain":[30023,30024,30025],"bChain":[40004,40005,40006],"hpGrowth":6,"atkGrowth":6,"spdGrowth":6,"defGrowth":6,"resGrowth":4,"movementType":"INFANTRY","weaponType":"GTOME"}
{"name":"RobinFSummer","weaponChain":[71,131,200,201],"assistChain":[10017],"aChain":[30014,30083,30084],"cChain":[50085,50086,50087],"hpGrowth":4,"atkGrowth":7,"spdGrowth":8,"defGrowth":6,"resGrowth":6,"movementType":"INFANTRY","weaponType":"LANCE"}
{"name":"RobinM","weaponChain":[134,34,12,13],"specialChain":[20019,20008],"aChain":[30026,30027,30028],"cChain":[50032,50033,50034],"hpGrowth":6,"atkGrowth":6,"spdGrowth":6,"defGrowth":6,"resGrowth":4,"movementType":"INFANTRY","weaponType":"BTOME"}
{"name":"Roderick","weaponChain":[71,131,189,187],"assistChain":[10010,10023],"bChain":[40019],"cChain":[50032,50071,50072],"hpGrowth":6,"atkGrowth":7,"spdGrowth":8,"defGrowth":5,"resGrowth":4,"movementType":"CAVALRY","weaponType":"LANCE"}
{"name":"Roy","weaponChain":[72,132,122,9],"assistChain":[10018],"aChain":[30046,30047,30048],"bChain":[40055,40056,40057],"hpGrowth":7,"atkGrowth":6,"spdGrowth":6,"defGrowth":5,"resGrowth":7,"movementType":"INFANTRY","weaponType":"SWORD"}
{"name":"Ryoma","weaponChain":[72,132,122,97],"specialChain":[20034,20003],"aChain":[30017,30018,30019],"cChain":[50023,50024,50025],"hpGrowth":6,"atkGrowth":8,"spdGrowth":7,"defGrowth":6,"resGrowth":4,"movementType":"INFANTRY","weaponType":"SWORD"}
{"name":"Saizo","weaponChain":[70,130,125,126],"assistChain":[10003],"bChain":[40040,40041,40042],"cChain":[50038,50039,50040],"hpGrowth":5,"atkGrowth":6,"spdGrowth":8,"defGrowth":7,"resGrowth":2,"movementType":"INFANTRY","weaponType":"DAGGER"}
{"name":"Sakura","weaponChain":[7,40],"specialChain":[20028,20046],"assistChain":[10004,10006,10007],"cChain":[50006,50007,50008],"hpGrowth":5,"atkGrowth":6,"spdGrowth":6,"defGrowth":5,"resGrowth":6,"movementType":"INFANTRY","weaponType":"STAFF"}
{"name":"Sanaki","weaponChain":[44,33,16,27],"assistChain":[10003],"aChain":[30046,30047,30048],"cChain":[50018,50019,50020],"hpGrowth":4,"atkGrowth":9,"spdGrowth":5,"defGrowth":2,"resGrowth":8,"movementType":"INFANTRY","weaponType":"RTOME"}
{"name":"Selena","weaponChain":[72,132,3,4],"assistChain":[10017],"aChain":[30046,30047,30048],"cChain":[50050,50051,50052],"hpGrowth":5,"atkGrowth":5,"spdGrowth":8,"defGrowth":7,"resGrowth":6,"movementType":"INFANTRY","weaponType":"SWORD"}
{"name":"Seliph","weaponChain":[72,132,122,135],"assistChain":[10012],"aChain":[30033,30034,30035],"bChain":[40010,40011,40012],"hpGrowth":9,"atkGrowth":8,"spdGrowth":4,"defGrowth":6,"resGrowth":4,"movementType":"INFANTRY","weaponType":"SWORD"}
{"name":"Serra","weaponChain":[7,1],"specialChain":[20028,20047],"assistChain":[10004,10006,10015],"cChain":[50018,50019,50020],"hpGrowth":4,"atkGrowth":7,"spdGrowth":6,"defGrowth":4,"resGrowth":7,"movementType":"INFANTRY","weaponType":"STAFF"}
{"name":"Setsuna","weaponChain":[69,129,5,6],"assistChain":[10013],"aChain":[30033,30034,30035],"bChain":[40007,40008,40009],"hpGrowth":5,"atkGrowth":6,"spdGrowth":9,"defGrowth":4,"resGrowth":4,"movementType":"INFANTRY","weaponType":"BOW"}
{"name":"Shanna","weaponChain":[71,131,77,78],"specialChain":[20010,20026],"bChain":[40016,40017,40018],"cChain":[50050,50051,50052],"hpGrowth":6,"atkGrowth":6,"spdGrowth":8,"defGrowth":5,"resGrowth":6,"movementType":"FLIER","weaponType":"LANCE"}
{"name":"Sharena","weaponChain":[71,131,120,43],"assistChain":[10009],"aChain":[30042,30043,30044],"cChain":[50006,50007,50008],"hpGrowth":7,"atkGrowth":7,"spdGrowth":7,"defGrowth":6,"resGrowth":4,"movementType":"INFANTRY","weaponType":"LANCE"}
{"name":"Sheena","weaponChain":[68,128,73,74],"specialChain":[20009,20015],"aChain":[30045],"cChain":[50006,50007,50004],"hpGrowth":7,"atkGrowth":6,"spdGrowth":5,"defGrowth":7,"resGrowth":8,"movementType":"ARMOR","weaponType":"AXE"}
{"name":"Sophia","weaponChain":[53,109,41,42],"specialChain":[20014,20013],"aChain":[30049,30050,30051],"cChain":[50011,50012,50013],"hpGrowth":6,"atkGrowth":7,"spdGrowth":3,"defGrowth":6,"resGrowth":6,"movementType":"INFANTRY","weaponType":"RTOME"}
{"name":"Soren","weaponChain":[136,35,104,148],"specialChain":[20042,20023],"bChain":[40082,40083,40084],"cChain":[50011,50012,50013],"hpGrowth":5,"atkGrowth":8,"spdGrowth":7,"defGrowth":2,"resGrowth":6,"movementType":"INFANTRY","weaponType":"GTOME"}
{"name":"Stahl","weaponChain":[72,132,107,108],"assistChain":[10021],"aChain":[30014,30015,30016],"bChain":[40034,40035,40036],"hpGrowth":8,"atkGrowth":7,"spdGrowth":5,"defGrowth":6,"resGrowth":4,"movementType":"CAVALRY","weaponType":"SWORD"}
{"name":"Subaki","weaponChain":[71,131,110,111],"assistChain":[10021],"aChain":[30039,30040,30041],"bChain":[40043,40044,40045],"hpGrowth":6,"atkGrowth":5,"spdGrowth":8,"defGrowth":8,"resGrowth":4,"movementType":"FLIER","weaponType":"LANCE"}
{"name":"Sully","weaponChain":[71,131,110,111],"assistChain":[10002],"bChain":[40064,40065,40066],"cChain":[50032,50033,50034],"hpGrowth":7,"atkGrowth":5,"spdGrowth":8,"defGrowth":4,"resGrowth":6,"movementType":"CAVALRY","weaponType":"LANCE"}
{"name":"Takumi","weaponChain":[69,129,116,55],"specialChain":[20038,20048],"aChain":[30007],"cChain":[50050,50051,50052],"hpGrowth":6,"atkGrowth":7,"spdGrowth":8,"defGrowth":5,"resGrowth":2,"movementType":"INFANTRY","weaponType":"BOW"}
{"name":"Tharja","weaponChain":[53,109,98,99],"specialChain":[20038,20048],"aChain":[30008,30009,30010],"cChain":[50035,50036,50037],"hpGrowth":6,"atkGrowth":7,"spdGrowth":8,"defGrowth":4,"resGrowth":3,"movementType":"INFANTRY","weaponType":"RTOME"}
{"name":"Tiki","weaponChain":[45,50,87,88],"specialChain":[20019,20008],"aChain":[30017,30018,30019],"cChain":[50035,50036,50037],"hpGrowth":6,"atkGrowth":9,"spdGrowth":4,"defGrowth":8,"resGrowth":4,"movementType":"INFANTRY","weaponType":"RBREATH"}
{"name":"Tiki_Young","weaponChain":[68,128,198,199],"specialChain":[20011,20044],"aChain":[30080,30081,30082],"cChain":[50082,50083,50084],"hpGrowth":8,"atkGrowth":8,"spdGrowth":8,"defGrowth":7,"resGrowth":6,"movementType":"INFANTRY","weaponType":"RBREATH"}
{"name":"TikiSummer","weaponChain":[45,50,51,52],"specialChain":[20039,20020],"aChain":[30001,30002,30003],"cChain":[50001,50002,50003],"hpGrowth":4,"atkGrowth":9,"spdGrowth":7,"defGrowth":7,"resGrowth":4,"movementType":"INFANTRY","weaponType":"AXE"}
{"name":"Titania","weaponChain":[68,128,36,37],"assistChain":[10013],"aChain":[30001,30002,30003],"bChain":[40085,40086,40087],"hpGrowth":5,"atkGrowth":6,"spdGrowth":8,"defGrowth":5,"resGrowth":6,"movementType":"CAVALRY","weaponType":"AXE"}
{"name":"Ursula","weaponChain":[134,34,14,15],"specialChain":[20041,20022],"aChain":[30011,30012,30013],"cChain":[50047,50048,50049],"hpGrowth":5,"atkGrowth":6,"spdGrowth":7,"defGrowth":3,"resGrowth":6,"movementType":"CAVALRY","weaponType":"BTOME"}
{"name":"Virion","weaponChain":[69,129,116,117],"specialChain":[20034,20003],"aChain":[30023,30024,30025],"bChain":[40061,40062,40063],"hpGrowth":8,"atkGrowth":7,"spdGrowth":7,"defGrowth":5,"resGrowth":1,"movementType":"INFANTRY","weaponType":"BOW"}
{"name":"Wrys","weaponChain":[7,124],"specialChain":[20028,20024],"assistChain":[10004,10014,10016],"bChain":[40030,40031,40032],"hpGrowth":7,"atkGrowth":5,"spdGrowth":4,"defGrowth":4,"resGrowth":8,"movementType":"INFANTRY","weaponType":"STAFF"}
{"name":"Xander","weaponChain":[72,132,122,149],"specialChain":[20040,20005],"aChain":[30001,30002,30003],"cChain":[50032,50033,50034],"hpGrowth":7,"atkGrowth":7,"spdGrowth":5,"defGrowth":9,"resGrowth":2,"movementType":"CAVALRY","weaponType":"SWORD"}
{"name":"XanderEaster","weaponChain":[71,131,165,141],"assistChain":[10021],"bChain":[40076],"cChain":[50006,50007,50008],"hpGrowth":6,"atkGrowth":5,"spdGrowth":6,"defGrowth":8,"resGrowth":5,"movementType":"CAVALRY","weaponType":"LANCE"}
{"name":"Zephiel","weaponChain":[72,132,122,146],"specialChain":[20038,20037],"aChain":[30036,30037,30038],"bChain":[40070,40071,40072],"hpGrowth":10,"atkGrowth":8,"spdGrowth":2,"defGrowth":8,"resGrowth":5,"movementType":"ARMOR","weaponType":"SWORD"}
